spooner/__init__.py
spooner/spooner.py
spooner-0.5.11.dist-info/LICENSE
spooner-0.5.11.dist-info/WHEEL
spooner-0.5.11.dist-info/METADATA
spooner-0.5.11.dist-info/RECORD
