Metadata-Version: 2.1
Name: spooner
Version: 0.5.11
Summary: spooner
Home-page: https://github.com/danmaps/spooner
License: UNKNOWN
Author: Danny McVey
Author-email: 
Classifier: License :: OSI Approved :: MIT License
Requires-Dist: nltk
Requires-Dist: pronouncing
Requires-Dist: pytest; extra == "test"
Requires-Dist: pytest-cov; extra == "test"
Requires-Dist: tox; extra == "test"
Provides-Extra: test
